ee_wildfire/UserInterface.py
ee_wildfire/__init__.py
ee_wildfire/build_dataset.py
ee_wildfire/command_line_args.py
ee_wildfire/constants.py
ee_wildfire/convert_tiff_to_hdf5.py
ee_wildfire/create_fire_config.py
ee_wildfire/drive_downloader.py
ee_wildfire/globfire.py
ee_wildfire/main.py
ee_wildfire/DataPreparation/DatasetPrepareService.py
ee_wildfire/DataPreparation/__init__.py
ee_wildfire/DataPreparation/satellites/FirePred.py
ee_wildfire/DataPreparation/satellites/__init__.py
ee_wildfire/UserConfig/UserConfig.py
ee_wildfire/UserConfig/__init__.py
ee_wildfire/UserConfig/authentication.py
ee_wildfire/UserConfig/user_config.yml
ee_wildfire/config/us_fire_2018_1e2.yml
ee_wildfire/config/us_fire_2018_1e3.yml
ee_wildfire/config/us_fire_2018_1e8.yml
ee_wildfire/config/us_fire_2020_1e3.yml
ee_wildfire/config/us_fire_2020_1e7.yml
ee_wildfire/config/us_fire_2021_1e0.yml
ee_wildfire/config/us_fire_2021_1e1.000000e+00.yml
ee_wildfire/config/us_fire_2021_1e1.yml
ee_wildfire/config/us_fire_2021_1e2.yml
ee_wildfire/config/us_fire_2021_1e3.yml
ee_wildfire/config/us_fire_2021_1e4.yml
ee_wildfire/config/us_fire_2021_1e6.yml
ee_wildfire/config/us_fire_2021_1e7.yml
ee_wildfire/utils/google_drive_util.py
ee_wildfire/utils/user_config_utils.py
ee_wildfire/utils/yaml_utils.py
ee_wildfire-2025.6.14.dist-info/licenses/LICENSE
ee_wildfire-2025.6.14.dist-info/METADATA
ee_wildfire-2025.6.14.dist-info/WHEEL
ee_wildfire-2025.6.14.dist-info/entry_points.txt
ee_wildfire-2025.6.14.dist-info/top_level.txt
ee_wildfire-2025.6.14.dist-info/RECORD
