Metadata-Version: 2.4
Name: ee-wildfire
Version: 2025.6.14
Summary: Pulls data from Google Earth Engine, syncs it to Google Drive, and downloads files.
Author-email: Jake Bova <developer.montana@gmail.com>, Lorn Jaeger <lornjaeger@proton.me>, Kyle Krstulich <kylekrstulich@gmail.com>
Maintainer-email: Kyle Krstulich <kylekrstulich@gmail.com>, Lorn Jaeger <lornjaeger@proton.me>
License: MIT License
Project-URL: Homepage, https://github.com/KylesCorner/Earth-Engine-Wildfire-Data/tree/master
Project-URL: Issues, https://github.com/KylesCorner/Earth-Engine-Wildfire-Data/issues
Keywords: wildfire,earth engine
Classifier: Development Status :: 5 - Production/Stable
Classifier: Programming Language :: Python
Requires-Python: >=3.10
License-File: LICENSE
Requires-Dist: earthengine-api
Requires-Dist: tqdm
Requires-Dist: pandas
Requires-Dist: raster_tools
Requires-Dist: geopandas
Requires-Dist: shapely
Requires-Dist: numpy
Requires-Dist: geemap
Requires-Dist: tdqm
Requires-Dist: google-api-python-client
Requires-Dist: google-auth-httplib2
Requires-Dist: google-auth-oauthlib
Requires-Dist: setuptools
Requires-Dist: wheel
Requires-Dist: prompt_toolkit
Requires-Dist: colorama
Dynamic: license-file
